h3pandas/__init__.py
h3pandas/const.py
h3pandas/h3pandas.py
h3pandas/__pycache__/__init__.cpython-311.pyc
h3pandas/__pycache__/__init__.cpython-312.pyc
h3pandas/__pycache__/_version.cpython-311.pyc
h3pandas/__pycache__/const.cpython-311.pyc
h3pandas/__pycache__/h3pandas.cpython-311.pyc
h3pandas/__pycache__/h3pandas.cpython-312.pyc
h3pandas/util/__init__.py
h3pandas/util/decorator.py
h3pandas/util/functools.py
h3pandas/util/shapely.py
h3pandas/util/__pycache__/__init__.cpython-311.pyc
h3pandas/util/__pycache__/decorator.cpython-311.pyc
h3pandas/util/__pycache__/functools.cpython-311.pyc
h3pandas/util/__pycache__/shapely.cpython-311.pyc
h3pandas-0.3.0.dist-info/LICENSE
h3pandas-0.3.0.dist-info/METADATA
h3pandas-0.3.0.dist-info/WHEEL
h3pandas-0.3.0.dist-info/top_level.txt
h3pandas-0.3.0.dist-info/RECORD
