Metadata-Version: 2.2
Name: h3pandas
Version: 0.3.0
Summary: Integration of H3 and GeoPandas
Author-email: Dahn <dahnjahn@gmail.com>
License: MIT License
Project-URL: Homepage, https://github.com/DahnJ/H3-Pandas
Project-URL: Download, https://github.com/DahnJ/H3-Pandas/releases
Requires-Python: >=3.9
License-File: LICENSE
Requires-Dist: geopandas
Requires-Dist: numpy
Requires-Dist: pandas
Requires-Dist: shapely
Requires-Dist: h3>=4
Requires-Dist: typing-extensions
Provides-Extra: test
Requires-Dist: pytest; extra == "test"
Requires-Dist: pytest-cov; extra == "test"
Requires-Dist: ruff; extra == "test"
Provides-Extra: docs
Requires-Dist: sphinx; extra == "docs"
Requires-Dist: numpydoc; extra == "docs"
Requires-Dist: pytest-sphinx-theme; extra == "docs"
Requires-Dist: typing-extensions; extra == "docs"
